jellyfish/cli.py
jellyfish/dynamite/__init__.py
jellyfish/dynamite/analysis_service.py
jellyfish/dynamite/ascii_art.py
jellyfish/dynamite/bandpass.py
jellyfish/dynamite/batch.py
jellyfish/dynamite/config.py
jellyfish/dynamite/diagnose.py
jellyfish/dynamite/dynamo.py
jellyfish/dynamite/jelly_app.py
jellyfish/dynamite/jellyfish_dynamite_browser.py
jellyfish/dynamite/jellyfish_dynamite_previous.py
jellyfish/dynamite/ordinalpeaks.py
jellyfish/dynamite/peaks.py
jellyfish/dynamite/psd.py
jellyfish/dynamite/psd_wavelets.py
jellyfish/dynamite/ridge.py
jellyfish/dynamite/saving.py
jellyfish/dynamite/smooth.py
jellyfish/dynamite/spectro.py
jellyfish/dynamite/strata.py
jellyfish/dynamite/veins.py
jellyfish/scraper/__init__.py
jellyfish/scraper/config.py
jellyfish/scraper/scrape.py
jellyfish/scraper/sources/__init__.py
jellyfish/scraper/sources/animalsounds.py
jellyfish/scraper/sources/base.py
jellyfish/scraper/sources/ebird.py
jellyfish/scraper/sources/freesound.py
jellyfish/scraper/sources/macaulay.py
jellyfish/scraper/sources/xenocanto.py
jellyfish/scraper/sources/youtube.py
jellyfish/testing/__init__.py
jellyfish/testing/ssim.py
jellyfish/testing/trill_metrics.py
jellyfish/tracer/__init__.py
jellyfish/tracer/trace.py
jellyfish/tranche/__init__.py
jellyfish/tranche/core/__init__.py
jellyfish/tranche/core/directory_manager.py
jellyfish/tranche/core/metadata_manager.py
jellyfish/tranche/core/slicer.py
jellyfish/tranche/parsers/__init__.py
jellyfish/tranche/parsers/audacity_parser.py
jellyfish/tranche/parsers/avianz_parser.py
jellyfish/tranche/parsers/base_parser.py
jellyfish/tranche/parsers/excel_parser.py
jellyfish/tranche/parsers/raven_parser.py
jellyfish/tranche/parsers/timeslist_parser.py
jellyfish/tranche/parsers/tsv_parser.py
jellyfish/utils/__init__.py
jellyfish/utils/bandpass.py
jellyfish/utils/format_text_annotations.py
jellyfish/utils/interactive_backend.py
jellyfish/utils/jelly_funcs.py
jellyfish/utils/remove_duplicate_columns.py
jellyfish/utils/spec_plotter.py
jellyfish_dynamite-0.1.0.dist-info/METADATA
jellyfish_dynamite-0.1.0.dist-info/WHEEL
jellyfish_dynamite-0.1.0.dist-info/top_level.txt
jellyfish_dynamite-0.1.0.dist-info/RECORD
